nbsfoodpricecleaner/__init__.py
nbsfoodpricecleaner/data_cleaner.py
nbsfoodpricecleaner-0.0.4.dist-info/METADATA
nbsfoodpricecleaner-0.0.4.dist-info/WHEEL
nbsfoodpricecleaner-0.0.4.dist-info/top_level.txt
nbsfoodpricecleaner-0.0.4.dist-info/RECORD
