Metadata-Version: 2.1
Name: nbsfoodpricecleaner
Version: 0.0.4
Summary: A Python package for cleaning and processing NBS food price data.
Home-page: https://github.com/prof2022/nbsfoodpricecleanerpkg
Author: prof2022
Author-email: jibrinharuna07@gmail.com
License: MIT
Project-URL: Bug Tracker, https://github.com/prof2022/nbsfoodpricecleanerpkg/issues
Classifier: Programming Language :: Python :: 3.7
Classifier: Programming Language :: Python :: 3.8
Classifier: Programming Language :: Python :: 3.9
Classifier: Programming Language :: Python :: 3.10
Classifier: Operating System :: OS Independent
Classifier: License :: OSI Approved :: MIT License
Classifier: Topic :: Software Development :: Libraries
Requires-Python: >=3.7
Requires-Dist: pandas>=1.3.0
Requires-Dist: numpy>=1.21.0
Provides-Extra: testing
Requires-Dist: pytest>=7.1.3; extra == "testing"
Requires-Dist: mypy>=0.971; extra == "testing"
Requires-Dist: flake8>=5.0.4; extra == "testing"
Requires-Dist: tox>=3.25.1; extra == "testing"
Requires-Dist: black>=22.8.0; extra == "testing"
